Workbook

Sheet Liste
A1: Mot | B1: Définition | C1: Courte | D1: Jour | E1: Alea
A2: Quérimonie | B2: (ké-ri-mo-nie), n. f. 1°Terme d’officialité. Requête présentée au juge d’église, pour obtenir la permission d’adresser un monitoire. 2°Familièrement. Il s’est dit pour plainte en général. Finissez, finissez votre quérimonie, SCARRON. Après une longue et furieuse quérimonie, Mme de Roquelaure commença à découvrir le fait, SAINT-SIMON. | C2: Plainte solennelle ou doléance formulée par écrit en justice ou en liturgie. | D2: =TODAY()+1 -> 46168 | E2: 0.0082714884
A3: Concraire | B3: (kon-krê-r’), v. a. Terme de grammaire et de logique. Donner le caractère concret, par opposition à abstraire. | C3: Résister, s'opposer fermement à quelque chose en vieux français. | D3: =D2+1 -> 46169 | E3: 0.97748689
A4: Écornifleur | B4: Personne qui profite de la générosité des autres sans jamais rendre la pareille. | C4: Parasite, pique-assiette qui vit aux crochets des autres en quémandant. | D4: =D3+1 -> 46170 | E4: 0.63241814
A5: Valetet | B5: (va-le-tè), n. m. Nom donné au bord latéral du filet de pêche, Décret du 7 juin 1852. | C5: (ou Valeton) Jeune valet ou serviteur de bas étage au Moyen Âge (vieux français). | D5: =D4+1 -> 46171 | E5: 0.25508909
A6: Ganja | B6: (gan-ja), n. m. Préparation qui se fait avec les fleurs séchées du chanvre indien, Journ. offic. 5 janv. 1873, p. 58,1re col. | C6: Nom traditionnel d'origine indienne donné au chanvre indien (cannabis). | D6: =D5+1 -> 46172 | E6: 0.36623996
A7: Girie | B7: (ji-rie), n. f. Terme populaire. Plainte hypocrite, jérémiade ridicule. | C7: Plainte affectée, fausse jérémiade ou manières hypocrites pour attirer la pitié (surtout au pluriel giries). | D7: =D6+1 -> 46173 | E7: 0.5196653
A8: Docte | B8: (do-kt’), adj. Instruit, versé en toute sorte de connaissances littéraires. L’homme docte sert moins que l’homme pacifique, CORNEILLE. Par raillerie, une docte matrone, une femme savante. | C8: Qui possède un savoir approfondi, une grande érudition classique. | D8: =D7+1 -> 46174 | E8: 0.92564477
A9: Isocolon | B9: (i-zo-ko-lon), n. m. Terme de rhétorique. Période dont les membres sont égaux. | C9: Figure de style caractérisée par des membres de phrases de longueur et de structure grammaticale identiques. | D9: =D8+1 -> 46175 | E9: 0.74405275
A10: Oing | B10: (ouin ; le g ne se prononce jamais), n. m. Graisse. L’oing, qu’on appelle autrement axonge, est la graisse la plus molle et la plus humide du corps des animaux. | C10: (ou Vieux oing) Graisse de porc ou de bête purifiée servant à lubrifier les essieux des charrettes autrefois. | D10: =D9+1 -> 46176 | E10: 0.039787165
A11: Bonnette | B11: (bo-nè-t’), n. f. 1°Terme de fortification. Ouvrage avancé qui est au delà de la contrescarpe, en forme de petit corps de garde, et dont les deux faces forment un angle saillant 2°Terme de marine. Petites voiles qu’on ajoute aux grandes pour présenter une plus grande surface au vent. | C11: Voile additionnelle que l'on lace aux grandes voiles par beau temps pour augmenter la vitesse. | D11: =D10+1 -> 46177 | E11: 1.0397872
A12: Muant | B12: (mu-an), n. m. Bassin qui fait partie d’un marais salant. | C12: Animal ou oiseau qui est en période de mue, perdant ses poils ou ses plumes. | D12: =D11+1 -> 46178 | E12: 2.0397872
A13: Leu | B13: (leu), n. m. Ancien nom du loup. Usité seulement dans cette locution familière : à la queue leu leu, à la suite les uns des autres. | C13: Ancien mot de vieux français pour désigner le loup (utilisé dans "à la queue leu leu"). | D13: =D12+1 -> 46179 | E13: 3.0397872
A14: Mantelet | B14: (man-te-lè), n. m. Machine de guerre composée de madriers qu’on poussait devant soi pour se couvrir dans l’attaque des places. Sous de forts mantelets et d’épais gabions Elle vient s’attacher au pied des bastions, BRÉBEUF. | C14: Court manteau de femme sans manches ; ou lourd panneau de bois mobile protégeant les assiégeants. | D14: =D13+1 -> 46180 | E14: 4.0397872
... A1967: Quadrivium | B1967: (koua-dri-vi-om’), n. m. La division supérieure des sept arts dans l’université du moyen âge, division qui venait après le trivium et qui comprenait l’arithmétique, la géométrie, la musique et l’astronomie. | C1967: Les quatre sciences de l'enseignement supérieur médiéval comprenant l'arithmétique, la géométrie, l'astronomie et la musique. | D1967: =D1966+1 -> 48133 | E1967: 1957.0398
A1968: Exégète (s) | B1968: (è-gzé-jé-t’), n. m. Savant qui se consacre à l’explication et à l’interprétation des livres saints. | C1968: #N/A | D1968: =D1967+1 -> 48134 | E1968: 1958.0398
A1969: Vulpin | B1969: INE (vul-pin, pi-n’), adj. 1°Qui tient du renard 2°N. m. Terme de botanique. Genre de la famille des graminées. Vulpin, nommé aussi racouet, plante ainsi dite du latin vulpis, parce que l’épi est comparé à une queue de renard. | C1969: (Queue-de-rat) Plante herbeuse commune des prairies dont l'épi allongé ressemble à la queue d'un renard. | D1969: =D1968+1 -> 48135 | E1969: 1959.0398
A1970: Patrologie | B1970: (pa-tro-lo-jie), n. f. Connaissance particulière des Pères de l’Eglise. Édition de tous les Pères de l’Église. | C1970: Étude historique et théologique de la vie, des œuvres et des doctrines des Pères de l'Église. | D1970: =D1969+1 -> 48136 | E1970: 1960.0398
A1971: Avalaige | B1971: n. m. Pente douce, chemin pour descendre. (La Curne) | C1971: Action de descendre un cours d'eau en bateau ou de faire flotter du bois. | D1971: =D1970+1 -> 48137 | E1971: 1961.0398
A1972: Hobin | B1972: (ho-bin), n. m. Nom d’une race de chevaux d’Écosse qui vont naturellement l’amble. | C1972: Ancien cheval de selle écossais, d'allure rapide et d'une petite taille. | D1972: =D1971+1 -> 48138 | E1972: 1962.0398
A1973: Quartier-mestre | B1973: (kar-tié-mè-str’), n. m. Nom que l’on donnait autrefois au maréchal des logis d’un régiment de cavalerie étrangère. | C1973: Sous-officier de marine chargé des détails d'administration, des vivres ou de la manœuvre. | D1973: =D1972+1 -> 48139 | E1973: 1963.0398
A1974: Paillau | B1974: n. m. Portion. (La Curne) | C1974: (ou Paillot) Petit lit de paille, paillasse rustique ou natte de marin. | D1974: =D1973+1 -> 48140 | E1974: 1964.0398
A1975: Were | B1975: n. f. Guerre. " Grans pais, koi c’on die, Gist en grande were à le fie. " (Vatic. 1490, La Curne.) | C1975: Digue de terre ou barrage en maçonnerie construit le long d'une rivière en vieux français. | D1975: =D1974+1 -> 48141 | E1975: 1965.0398
A1976: Hétérobaphie | B1976: (é-té-ro-ba-fie), n. f. État d’un corps dont la surface est de deux ou de plusieurs couleurs. | C1976: Propriété d'un corps ou d'un tissu présentant des nuances de couleurs variées ou changeantes. | D1976: =D1975+1 -> 48142 | E1976: 1966.0398
A1977: Hague | B1977: (ha-gh’, h aspirée), n. f. Palissade. | C1977: Clôture faite de pieux de bois ou haie vive en vieux français régional. | D1977: =D1976+1 -> 48143 | E1977: 1967.0398
A1978: Rumb | B1978: (ronb’), n. m. 1°Terme de marine. Quantité angulaire comprise entre deux des trente-deux aires de vent de la boussole 2°Ligne de rumb, courbe que décrit un vaisseau, en faisant toujours le même angle avec le méridien. | C1978: Angle de cap mesurant 11°15', correspondant à l'une des 32 divisions de la rose des vents. | D1978: =D1977+1 -> 48144 | E1978: 1968.0398
A1979: Houka | B1979: (hou-ka), n. m. Pipe turque ou persane, peu différente du narghileh. | C1979: (ou Narguilé) Pipe orientale à eau dotée d'un long tuyau flexible pour fumer le tabac. | D1979: =D1978+1 -> 48145 | E1979: 1969.0398
A1980: Acrologique | B1980: (a-kro-lo-ji-k’), adj. Terme de grammaire. Qui appartient au commencement d’un mot. | C1980: Qui concerne l'utilisation de la première lettre d'un mot pour en représenter le son. | D1980: =D1979+1 -> 48146 | E1980: 1970.0398
... A4978: Bistourner | B4978: (bi-stour-né), v. t. 1°Tourner, courber un objet de manière à le déformer 2°Terme de vétérinaire. Châtrer un animal en tordant les vaisseaux testiculaires 3°Se bistourner, v. pr. Devenir bistourné. Ses jambes se sont bistournées. | C4978: Tordre un objet ; ou castrer un animal par torsion des vaisseaux sans incision. | D4978: =D4977+1 -> 51144 | E4978: 4968.0398

Sheet Feuil1
A1: Abscons : Très difficile à comprendre ; obscur, nébuleux. | B1: =LEN(A1) -> 61 | C1: =SEARCH(":",A1) -> 13 | D1: =LEFT(A1,C1-2) -> Abscons | E1: =LEN(D1) -> 11 | F1: Abscons | G1: Très difficile à comprendre ; obscur, nébuleux. | H1: =MATCH(F1,Liste!A:A,0) -> #N/A
A2: Alacrité : Gaieté vive et entraînante ; entrain. | B2: =LEN(A2) -> 52 | C2: =SEARCH(":",A2) -> 14 | D2: =LEFT(A2,C2-2) -> Alacrité | E2: =LEN(D2) -> 12 | F2: Alacrité | G2: Gaieté vive et entraînante ; entrain. | H2: =MATCH(F2,Liste!A:A,0) -> 1768
A3: Captieux : Qui cherche à tromper ou induire en erreur sous des apparences séduisantes. | B3: =LEN(A3) -> 90 | C3: =SEARCH(":",A3) -> 14 | D3: =LEFT(A3,C3-2) -> Captieux | E3: =LEN(D3) -> 12 | F3: Captieux | G3: Qui cherche à tromper ou induire en erreur sous des apparences séduisantes. | H3: =MATCH(F3,Liste!A:A,0) -> 3706
A4: Contempteur : Personne qui dénigre, méprise ou critique vivement. | B4: =LEN(A4) -> 69 | C4: =SEARCH(":",A4) -> 17 | D4: =LEFT(A4,C4-2) -> Contempteur | E4: =LEN(D4) -> 15 | F4: Contempteur | G4: Personne qui dénigre, méprise ou critique vivement. | H4: =MATCH(F4,Liste!A:A,0) -> 993
A5: Diatribe : Critique violente, amère et passionnée contre quelqu'un ou quelque chose. | B5: =LEN(A5) -> 88 | C5: =SEARCH(":",A5) -> 14 | D5: =LEFT(A5,C5-2) -> Diatribe | E5: =LEN(D5) -> 12 | F5: Diatribe | G5: Critique violente, amère et passionnée contre quelqu'un ou quelque chose. | H5: =MATCH(F5,Liste!A:A,0) -> #N/A
A6: Dilemme : Obligation de choisir entre deux partis comprenant tous deux des inconvénients. | B6: =LEN(A6) -> 93 | C6: =SEARCH(":",A6) -> 13 | D6: =LEFT(A6,C6-2) -> Dilemme | E6: =LEN(D6) -> 11 | F6: Dilemme | G6: Obligation de choisir entre deux partis comprenant tous deux des inconvénients. | H6: =MATCH(F6,Liste!A:A,0) -> #N/A
A7: Éburnéen : Qui a la blancheur ou la texture de l'ivoire. | B7: =LEN(A7) -> 60 | C7: =SEARCH(":",A7) -> 14 | D7: =LEFT(A7,C7-2) -> Éburnéen | E7: =LEN(D7) -> 12 | F7: Éburnéen | G7: Qui a la blancheur ou la texture de l'ivoire. | H7: =MATCH(F7,Liste!A:A,0) -> 4935
A8: Éristique : Art de la controverse, de la dispute philosophique. | B8: =LEN(A8) -> 67 | C8: =SEARCH(":",A8) -> 15 | D8: =LEFT(A8,C8-2) -> Éristique | E8: =LEN(D8) -> 13 | F8: Éristique | G8: Art de la controverse, de la dispute philosophique. | H8: =MATCH(F8,Liste!A:A,0) -> 4271
A9: Factice : Qui n'est pas naturel ; artificiel ou faux. | B9: =LEN(A9) -> 57 | C9: =SEARCH(":",A9) -> 13 | D9: =LEFT(A9,C9-2) -> Factice | E9: =LEN(D9) -> 11 | F9: Factice | G9: Qui n'est pas naturel ; artificiel ou faux. | H9: =MATCH(F9,Liste!A:A,0) -> #N/A
A10: Grivois : Qui est d'une gaieté libre, hardie, voire légèrement obscène. | B10: =LEN(A10) -> 75 | C10: =SEARCH(":",A10) -> 13 | D10: =LEFT(A10,C10-2) -> Grivois | E10: =LEN(D10) -> 11 | F10: Grivois | G10: Qui est d'une gaieté libre, hardie, voire légèrement obscène. | H10: =MATCH(F10,Liste!A:A,0) -> #N/A
A11: Hédonisme : Doctrine philosophique qui fait du plaisir le but de la vie. | B11: =LEN(A11) -> 76 | C11: =SEARCH(":",A11) -> 15 | D11: =LEFT(A11,C11-2) -> Hédonisme | E11: =LEN(D11) -> 13 | F11: Hédonisme | G11: Doctrine philosophique qui fait du plaisir le but de la vie. | H11: =MATCH(F11,Liste!A:A,0) -> #N/A
A12: Idiosyncrasie : Comportement ou réaction propre et particulière à un individu. | B12: =LEN(A12) -> 82 | C12: =SEARCH(":",A12) -> 19 | D12: =LEFT(A12,C12-2) -> Idiosyncrasie | E12: =LEN(D12) -> 17 | F12: Idiosyncrasie | G12: Comportement ou réaction propre et particulière à un individu. | H12: =MATCH(F12,Liste!A:A,0) -> #N/A
... A4642: Zymique : Qui appartient, se rapporte ou est propre aux fermentations chimiques. | B4642: =LEN(A4642) -> 84 | C4642: =SEARCH(":",A4642) -> 13 | D4642: =LEFT(A4642,C4642-2) -> Zymique | E4642: =LEN(D4642) -> 11 | F4642: Zymique | G4642: Qui appartient, se rapporte ou est propre aux fermentations chimiques. | H4642: =MATCH(F4642,Liste!A:A,0) -> 1123
A4643: Ébe (ou Jusant) : Période où la mer descend à marée basse (terme maritime). | B4643: =LEN(A4643) -> 79 | C4643: =SEARCH(":",A4643) -> 21 | D4643: =LEFT(A4643,C4643-2) -> Ébe (ou Jusant) | E4643: =LEN(D4643) -> 19 | F4643: Ébe | G4643: (ou Jusant) Période où la mer descend à marée basse (terme maritime). | H4643: =MATCH(F4643,Liste!A:A,0) -> 4770 | I4643: =LEN(F4643) -> 3 | J4643: =SEARCH(" (ou",F4643) -> #VALUE! | K4643: Ébe | L4643: (ou Jusant) Période où la mer descend à marée basse (terme maritime). | M4643: =LEFT(F4643,J4643-1) -> #VALUE! | N4643: =RIGHT(F4643,I4643-J4643)&" "&G4643 -> #VALUE!
A4644: Onc (ou Onques) : Mot de vieux français signifiant "jamais" (utilisé dans "oncques ne vit"). | B4644: =LEN(A4644) -> 96 | C4644: =SEARCH(":",A4644) -> 21 | D4644: =LEFT(A4644,C4644-2) -> Onc (ou Onques) | E4644: =LEN(D4644) -> 19 | F4644: Onc | G4644: (ou Onques) Mot de vieux français signifiant "jamais" (utilisé dans "oncques ne vit"). | H4644: =MATCH(F4644,Liste!A:A,0) -> 4195 | I4644: =LEN(F4644) -> 3 | J4644: =SEARCH(" (ou",F4644) -> #VALUE! | K4644: Onc | L4644: (ou Onques) Mot de vieux français signifiant "jamais" (utilisé dans "oncques ne vit"). | M4644: =LEFT(F4644,J4644-1) -> #VALUE! | N4644: =RIGHT(F4644,I4644-J4644)&" "&G4644 -> #VALUE!
A4645: Oue (ou Oye) : Mot de vieux français pour désigner l'oie. | B4645: =LEN(A4645) -> 61 | C4645: =SEARCH(":",A4645) -> 18 | D4645: =LEFT(A4645,C4645-2) -> Oue (ou Oye) | E4645: =LEN(D4645) -> 16 | F4645: Oue | G4645: (ou Oye) Mot de vieux français pour désigner l'oie. | H4645: =MATCH(F4645,Liste!A:A,0) -> 3663 | I4645: =LEN(F4645) -> 3 | J4645: =SEARCH(" (ou",F4645) -> #VALUE! | K4645: Oue | L4645: (ou Oye) Mot de vieux français pour désigner l'oie. | M4645: =LEFT(F4645,J4645-1) -> #VALUE! | N4645: =RIGHT(F4645,I4645-J4645)&" "&G4645 -> #VALUE!
A4646: Ure (ou Aurochs) : Bœuf sauvage préhistorique géant aujourd'hui disparu, ancêtre de nos races de bétail. | B4646: =LEN(A4646) -> 108 | C4646: =SEARCH(":",A4646) -> 22 | D4646: =LEFT(A4646,C4646-2) -> Ure (ou Aurochs) | E4646: =LEN(D4646) -> 20 | F4646: Ure | G4646: (ou Aurochs) Bœuf sauvage préhistorique géant aujourd'hui disparu, ancêtre de nos races de bétail. | H4646: =MATCH(F4646,Liste!A:A,0) -> 2453 | I4646: =LEN(F4646) -> 3 | J4646: =SEARCH(" (ou",F4646) -> #VALUE! | K4646: Ure | L4646: (ou Aurochs) Bœuf sauvage préhistorique géant aujourd'hui disparu, ancêtre de nos races de bétail. | M4646: =LEFT(F4646,J4646-1) -> #VALUE! | N4646: =RIGHT(F4646,I4646-J4646)&" "&G4646 -> #VALUE!
A4647: Yac (ou Yack) : Grand mammifère ruminant des plateaux du Tibet couvert d'une longue toison de poils laineux. | B4647: =LEN(A4647) -> 112 | C4647: =SEARCH(":",A4647) -> 19 | D4647: =LEFT(A4647,C4647-2) -> Yac (ou Yack) | E4647: =LEN(D4647) -> 17 | F4647: Yac | G4647: (ou Yack) Grand mammifère ruminant des plateaux du Tibet couvert d'une longue toison de poils laineux. | H4647: =MATCH(F4647,Liste!A:A,0) -> 1236 | I4647: =LEN(F4647) -> 3 | J4647: =SEARCH(" (ou",F4647) -> #VALUE! | K4647: Yac | L4647: (ou Yack) Grand mammifère ruminant des plateaux du Tibet couvert d'une longue toison de poils laineux. | M4647: =LEFT(F4647,J4647-1) -> #VALUE! | N4647: =RIGHT(F4647,I4647-J4647)&" "&G4647 -> #VALUE!
A4648: Zec (ou Zéquin) : Ancienne pièce de monnaie d'or frappée à Venise, très recherchée pour sa pureté autrefois. | B4648: =LEN(A4648) -> 112 | C4648: =SEARCH(":",A4648) -> 21 | D4648: =LEFT(A4648,C4648-2) -> Zec (ou Zéquin) | E4648: =LEN(D4648) -> 19 | F4648: Zec | G4648: (ou Zéquin) Ancienne pièce de monnaie d'or frappée à Venise, très recherchée pour sa pureté autrefois. | H4648: =MATCH(F4648,Liste!A:A,0) -> 2821 | I4648: =LEN(F4648) -> 3 | J4648: =SEARCH(" (ou",F4648) -> #VALUE! | K4648: Zec | L4648: (ou Zéquin) Ancienne pièce de monnaie d'or frappée à Venise, très recherchée pour sa pureté autrefois. | M4648: =LEFT(F4648,J4648-1) -> #VALUE! | N4648: =RIGHT(F4648,I4648-J4648)&" "&G4648 -> #VALUE!
A4649: Biez (ou Bief) : Canal de dérivation qui conduit l'eau d'une rivière jusqu'à la roue d'un moulin. | B4649: =LEN(A4649) -> 101 | C4649: =SEARCH(":",A4649) -> 20 | D4649: =LEFT(A4649,C4649-2) -> Biez (ou Bief) | E4649: =LEN(D4649) -> 18 | F4649: Biez | G4649: (ou Bief) Canal de dérivation qui conduit l'eau d'une rivière jusqu'à la roue d'un moulin. | H4649: =MATCH(F4649,Liste!A:A,0) -> 1610 | I4649: =LEN(F4649) -> 4 | J4649: =SEARCH(" (ou",F4649) -> #VALUE! | K4649: Biez | L4649: (ou Bief) Canal de dérivation qui conduit l'eau d'une rivière jusqu'à la roue d'un moulin. | M4649: =LEFT(F4649,J4649-1) -> #VALUE! | N4649: =RIGHT(F4649,I4649-J4649)&" "&G4649 -> #VALUE!
A4650: Glai (ou Glaie) : Sorte de plante aquatique des marais ressemblant à l'iris (le glaïeul sauvage). | B4650: =LEN(A4650) -> 101 | C4650: =SEARCH(":",A4650) -> 21 | D4650: =LEFT(A4650,C4650-2) -> Glai (ou Glaie) | E4650: =LEN(D4650) -> 19 | F4650: Glai | G4650: (ou Glaie) Sorte de plante aquatique des marais ressemblant à l'iris (le glaïeul sauvage). | H4650: =MATCH(F4650,Liste!A:A,0) -> 3613 | I4650: =LEN(F4650) -> 4 | J4650: =SEARCH(" (ou",F4650) -> #VALUE! | K4650: Glai | L4650: (ou Glaie) Sorte de plante aquatique des marais ressemblant à l'iris (le glaïeul sauvage). | M4650: =LEFT(F4650,J4650-1) -> #VALUE! | N4650: =RIGHT(F4650,I4650-J4650)&" "&G4650 -> #VALUE!
A4651: Gone (ou Gonne) : Tunique longue portée au Moyen Âge ; ou enfant dans le parler lyonnais moderne. | B4651: =LEN(A4651) -> 101 | C4651: =SEARCH(":",A4651) -> 21 | D4651: =LEFT(A4651,C4651-2) -> Gone (ou Gonne) | E4651: =LEN(D4651) -> 19 | F4651: Gone | G4651: (ou Gonne) Tunique longue portée au Moyen Âge ; ou enfant dans le parler lyonnais moderne. | H4651: =MATCH(F4651,Liste!A:A,0) -> #N/A | I4651: =LEN(F4651) -> 4 | J4651: =SEARCH(" (ou",F4651) -> #VALUE! | K4651: Gone | L4651: (ou Gonne) Tunique longue portée au Moyen Âge ; ou enfant dans le parler lyonnais moderne. | M4651: =LEFT(F4651,J4651-1) -> #VALUE! | N4651: =RIGHT(F4651,I4651-J4651)&" "&G4651 -> #VALUE!
A4652: Naye (ou Naie) : Sorte de petite cheville ou de cale en bois rustique. | B4652: =LEN(A4652) -> 74 | C4652: =SEARCH(":",A4652) -> 20 | D4652: =LEFT(A4652,C4652-2) -> Naye (ou Naie) | E4652: =LEN(D4652) -> 18 | F4652: Naye | G4652: (ou Naie) Sorte de petite cheville ou de cale en bois rustique. | H4652: =MATCH(F4652,Liste!A:A,0) -> 2891 | I4652: =LEN(F4652) -> 4 | J4652: =SEARCH(" (ou",F4652) -> #VALUE! | K4652: Naye | L4652: (ou Naie) Sorte de petite cheville ou de cale en bois rustique. | M4652: =LEFT(F4652,J4652-1) -> #VALUE! | N4652: =RIGHT(F4652,I4652-J4652)&" "&G4652 -> #VALUE!
A4653: Oing (ou Vieux oing) : Graisse de porc ou de bête purifiée servant à lubrifier les essieux des charrettes autrefois. | B4653: =LEN(A4653) -> 120 | C4653: =SEARCH(":",A4653) -> 26 | D4653: =LEFT(A4653,C4653-2) -> Oing (ou Vieux oing) | E4653: =LEN(D4653) -> 24 | F4653: Oing | G4653: (ou Vieux oing) Graisse de porc ou de bête purifiée servant à lubrifier les essieux des charrettes autrefois. | H4653: =MATCH(F4653,Liste!A:A,0) -> 10 | I4653: =LEN(F4653) -> 4 | J4653: =SEARCH(" (ou",F4653) -> #VALUE! | K4653: Oing | L4653: (ou Vieux oing) Graisse de porc ou de bête purifiée servant à lubrifier les essieux des charrettes autrefois. | M4653: =LEFT(F4653,J4653-1) -> #VALUE! | N4653: =RIGHT(F4653,I4653-J4653)&" "&G4653 -> #VALUE!
A4654: Oost (ou Ost) : L'armée ou la campagne militaire féodale au Moyen Âge en vieux français. | B4654: =LEN(A4654) -> 92 | C4654: =SEARCH(":",A4654) -> 19 | D4654: =LEFT(A4654,C4654-2) -> Oost (ou Ost) | E4654: =LEN(D4654) -> 17 | F4654: Oost | G4654: (ou Ost) L'armée ou la campagne militaire féodale au Moyen Âge en vieux français. | H4654: =MATCH(F4654,Liste!A:A,0) -> 4683 | I4654: =LEN(F4654) -> 4 | J4654: =SEARCH(" (ou",F4654) -> #VALUE! | K4654: Oost | L4654: (ou Ost) L'armée ou la campagne militaire féodale au Moyen Âge en vieux français. | M4654: =LEFT(F4654,J4654-1) -> #VALUE! | N4654: =RIGHT(F4654,I4654-J4654)&" "&G4654 -> #VALUE!
... A4914: Chryséléphantin (ou Chryséléphantine) : Statue antique faite de plaques d'or (pour les draps) et d'ivoire (pour la chair), comme la statue de Zeus à Olympie. | B4914: =LEN(A4914) -> 161 | C4914: =SEARCH(":",A4914) -> 43 | D4914: =LEFT(A4914,C4914-2) -> Chryséléphantin (ou Chryséléphantine) | E4914: =LEN(D4914) -> 41 | F4914: Chryséléphantin | G4914: (ou Chryséléphantine) Statue antique faite de plaques d'or (pour les draps) et d'ivoire (pour la chair), comme la statue de Zeus à Olympie. | H4914: =MATCH(F4914,Liste!A:A,0) -> 4436 | I4914: =LEN(F4914) -> 15 | J4914: =SEARCH(" (ou",F4914) -> #VALUE! | K4914: Chryséléphantin | L4914: (ou Chryséléphantine) Statue antique faite de plaques d'or (pour les draps) et d'ivoire (pour la chair), comme la statue de Zeus à Olympie. | M4914: =LEFT(F4914,J4914-1) -> #VALUE! | N4914: =RIGHT(F4914,I4914-J4914)&" "&G4914 -> #VALUE!
A4915: Barde (armure/cuisine) : Armure de fer protégeant le cheval de guerre ; ou mince tranche de lard enveloppant une viande. | B4915: =LEN(A4915) -> 124 | C4915: =SEARCH(":",A4915) -> 28 | D4915: =LEFT(A4915,C4915-2) -> Barde (armure/cuisine) | E4915: =LEN(D4915) -> 26 | F4915: Barde | G4915: Armure de fer protégeant le cheval de guerre ; ou mince tranche de lard enveloppant une viande. | H4915: =MATCH(F4915,Liste!A:A,0) -> 2966 | I4915: =LEN(F4915) -> 5 | J4915: =SEARCH(" (ou",F4915) -> #VALUE! | K4915: #VALUE! | L4915: #VALUE! | M4915: =LEFT(F4915,J4915-1) -> #VALUE! | N4915: =RIGHT(F4915,I4915-J4915)&" "&G4915 -> #VALUE!
A4916: Barde (poète) : Poète et chanteur celte chargé de célébrer les exploits des héros. | B4916: =LEN(A4916) -> 86 | C4916: =SEARCH(":",A4916) -> 19 | D4916: =LEFT(A4916,C4916-2) -> Barde (poète) | E4916: =LEN(D4916) -> 17 | F4916: Barde | G4916: Poète et chanteur celte chargé de célébrer les exploits des héros. | H4916: =MATCH(F4916,Liste!A:A,0) -> 2966 | I4916: =LEN(F4916) -> 5 | J4916: =SEARCH(" (ou",F4916) -> #VALUE! | K4916: #VALUE! | L4916: #VALUE! | M4916: =LEFT(F4916,J4916-1) -> #VALUE! | N4916: =RIGHT(F4916,I4916-J4916)&" "&G4916 -> #VALUE!
A4917: Eleuthénie : Fête ou célébration de la liberté dans la Grèce antique. | B4917: =LEN(A4917) -> 73 | C4917: =SEARCH(":",A4917) -> 16 | D4917: =LEFT(A4917,C4917-2) -> Eleuthénie | E4917: =LEN(D4917) -> 14 | F4917: Eleuthénie | G4917: Fête ou célébration de la liberté dans la Grèce antique. | H4917: =MATCH(F4917,Liste!A:A,0) -> #N/A | I4917: =LEN(F4917) -> 10 | J4917: =SEARCH(" (ou",F4917) -> #VALUE! | K4917: #VALUE! | L4917: #VALUE! | M4917: =LEFT(F4917,J4917-1) -> #VALUE! | N4917: =RIGHT(F4917,I4917-J4917)&" "&G4917 -> #VALUE!
A4918: Éphélide (souvent au pluriel Éphélides) : Nom scientifique et médical donné aux taches de rousseur provoquées par le soleil. | B4918: =LEN(A4918) -> 128 | C4918: =SEARCH(":",A4918) -> 45 | D4918: =LEFT(A4918,C4918-2) -> Éphélide (souvent au pluriel Éphélides) | E4918: =LEN(D4918) -> 43 | F4918: Éphélide | G4918: Nom scientifique et médical donné aux taches de rousseur provoquées par le soleil. | H4918: =MATCH(F4918,Liste!A:A,0) -> 4213 | I4918: =LEN(F4918) -> 8 | J4918: =SEARCH(" (ou",F4918) -> #VALUE! | K4918: #VALUE! | L4918: #VALUE! | M4918: =LEFT(F4918,J4918-1) -> #VALUE! | N4918: =RIGHT(F4918,I4918-J4918)&" "&G4918 -> #VALUE!
A4919: Ridel : Rideau ou draperie de séparation au Moyen Âge. | B4919: =LEN(A4919) -> 58 | C4919: =SEARCH(":",A4919) -> 11 | D4919: =LEFT(A4919,C4919-2) -> Ridel | E4919: =LEN(D4919) -> 9 | F4919: Ridel | G4919: Rideau ou draperie de séparation au Moyen Âge. | H4919: =MATCH(F4919,Liste!A:A,0) -> #N/A | I4919: =LEN(F4919) -> 5 | J4919: =SEARCH(" (ou",F4919) -> #VALUE! | K4919: #VALUE! | L4919: #VALUE! | M4919: =LEFT(F4919,J4919-1) -> #VALUE! | N4919: =RIGHT(F4919,I4919-J4919)&" "&G4919 -> #VALUE!
A4920: Sacreplumet : Homme vaniteux et fier de sa tenue en vieux français. | B4920: =LEN(A4920) -> 71 | C4920: =SEARCH(":",A4920) -> 17 | D4920: =LEFT(A4920,C4920-2) -> Sacreplumet | E4920: =LEN(D4920) -> 15 | F4920: Sacreplumet | G4920: Homme vaniteux et fier de sa tenue en vieux français. | H4920: =MATCH(F4920,Liste!A:A,0) -> #N/A | I4920: =LEN(F4920) -> 11 | J4920: =SEARCH(" (ou",F4920) -> #VALUE! | K4920: #VALUE! | L4920: #VALUE! | M4920: =LEFT(F4920,J4920-1) -> #VALUE! | N4920: =RIGHT(F4920,I4920-J4920)&" "&G4920 -> #VALUE!
A4921: Saynète : Courte pièce de théâtre comique, légère et rapide comptant peu de personnages. | B4921: =LEN(A4921) -> 92 | C4921: =SEARCH(":",A4921) -> 13 | D4921: =LEFT(A4921,C4921-2) -> Saynète | E4921: =LEN(D4921) -> 11 | F4921: Saynète | G4921: Courte pièce de théâtre comique, légère et rapide comptant peu de personnages. | H4921: =MATCH(F4921,Liste!A:A,0) -> #N/A | I4921: =LEN(F4921) -> 7 | J4921: =SEARCH(" (ou",F4921) -> #VALUE! | K4921: #VALUE! | L4921: #VALUE! | M4921: =LEFT(F4921,J4921-1) -> #VALUE! | N4921: =RIGHT(F4921,I4921-J4921)&" "&G4921 -> #VALUE!
A4922: Lambrequin (souvent au pluriel Lambrequins) : Longs rubans de tissu découpés ornant le timbre du casque d'un chevalier ; ou bordure découpée de toit. | B4922: =LEN(A4922) -> 149 | C4922: =SEARCH(":",A4922) -> 45 | D4922: =LEFT(A4922,C4922-2) -> Lambrequin (souvent au pluriel Lambrequins) | E4922: =LEN(D4922) -> 43 | F4922: Lambrequin | G4922: Longs rubans de tissu découpés ornant le timbre du casque d'un chevalier ; ou bordure découpée de toit. | H4922: =MATCH(F4922,Liste!A:A,0) -> 2132 | I4922: =LEN(F4922) -> 10 | J4922: =SEARCH(" (ou",F4922) -> #VALUE! | K4922: #VALUE! | L4922: #VALUE! | M4922: =LEFT(F4922,J4922-1) -> #VALUE! | N4922: =RIGHT(F4922,I4922-J4922)&" "&G4922 -> #VALUE!
A4923: Linéament (souvent au pluriel Linéaments) : Premiers traits d'un dessin ; ou premières ébauches d'un projet ou d'une idée. | B4923: =LEN(A4923) -> 122 | C4923: =SEARCH(":",A4923) -> 43 | D4923: =LEFT(A4923,C4923-2) -> Linéament (souvent au pluriel Linéaments) | E4923: =LEN(D4923) -> 41 | F4923: Linéament | G4923: Premiers traits d'un dessin ; ou premières ébauches d'un projet ou d'une idée. | H4923: =MATCH(F4923,Liste!A:A,0) -> 378 | I4923: =LEN(F4923) -> 9 | J4923: =SEARCH(" (ou",F4923) -> #VALUE! | K4923: #VALUE! | L4923: #VALUE! | M4923: =LEFT(F4923,J4923-1) -> #VALUE! | N4923: =RIGHT(F4923,I4923-J4923)&" "&G4923 -> #VALUE!
A4924: Voussoir : Pierre taillée en coin formant le cintre d'une arche ou d'une voûte en maçonnerie. | B4924: =LEN(A4924) -> 93 | C4924: =SEARCH(":",A4924) -> 10 | D4924: =LEFT(A4924,C4924-2) -> Voussoir | E4924: =LEN(D4924) -> 8 | F4924: Voussoir | G4924: Pierre taillée en coin formant le cintre d'une arche ou d'une voûte en maçonnerie. | H4924: =MATCH(F4924,Liste!A:A,0) -> #N/A | I4924: =LEN(F4924) -> 8 | J4924: =SEARCH(" (ou",F4924) -> #VALUE! | K4924: #VALUE! | L4924: #VALUE! | M4924: =LEFT(F4924,J4924-1) -> #VALUE! | N4924: =RIGHT(F4924,I4924-J4924)&" "&G4924 -> #VALUE!
A4925: Xénélansie : Expulsion ou interdiction d'accès faite aux étrangers dans la cité de Sparte antique. | B4925: =LEN(A4925) -> 98 | C4925: =SEARCH(":",A4925) -> 12 | D4925: =LEFT(A4925,C4925-2) -> Xénélansie | E4925: =LEN(D4925) -> 10 | F4925: Xénélansie | G4925: Expulsion ou interdiction d'accès faite aux étrangers dans la cité de Sparte antique. | H4925: =MATCH(F4925,Liste!A:A,0) -> #N/A | I4925: =LEN(F4925) -> 10 | J4925: =SEARCH(" (ou",F4925) -> #VALUE! | K4925: #VALUE! | L4925: #VALUE! | M4925: =LEFT(F4925,J4925-1) -> #VALUE! | N4925: =RIGHT(F4925,I4925-J4925)&" "&G4925 -> #VALUE!
A4926: Zélateur : Partisan fervent, défenseur plein de zèle et enthousiaste d'une cause ou d'une doctrine. | B4926: =LEN(A4926) -> 99 | C4926: =SEARCH(":",A4926) -> 10 | D4926: =LEFT(A4926,C4926-2) -> Zélateur | E4926: =LEN(D4926) -> 8 | F4926: Zélateur | G4926: Partisan fervent, défenseur plein de zèle et enthousiaste d'une cause ou d'une doctrine. | H4926: =MATCH(F4926,Liste!A:A,0) -> #N/A | I4926: =LEN(F4926) -> 8 | J4926: =SEARCH(" (ou",F4926) -> #VALUE! | K4926: #VALUE! | L4926: #VALUE! | M4926: =LEFT(F4926,J4926-1) -> #VALUE! | N4926: =RIGHT(F4926,I4926-J4926)&" "&G4926 -> #VALUE!
A4927: Pagale (En pagale) : En grand désordre, pêle-mêle (origine maritime, variante de pataquès). | B4927: =LEN(A4927) -> 91 | C4927: =SEARCH(":",A4927) -> 20 | D4927: =LEFT(A4927,C4927-2) -> Pagale (En pagale) | E4927: =LEN(D4927) -> 18 | F4927: Pagale | G4927: (En pagale) En grand désordre, pêle-mêle (origine maritime, variante de pataquès). | H4927: =MATCH(F4927,Liste!A:A,0) -> 4008 | I4927: =LEN(F4927) -> 6 | J4927: =SEARCH(" (",F4927) -> #VALUE! | K4927: Pagale | L4927: (En pagale) En grand désordre, pêle-mêle (origine maritime, variante de pataquès). | M4927: =LEFT(F4927,J4927-1) -> #VALUE! | N4927: =RIGHT(F4927,I4927-J4927)&" "&G4927 -> #VALUE!
A4928: Panader (Se panader) : Marcher fièrement en se pavanant et en prenant des airs importants. | B4928: =LEN(A4928) -> 90 | C4928: =SEARCH(":",A4928) -> 22 | D4928: =LEFT(A4928,C4928-2) -> Panader (Se panader) | E4928: =LEN(D4928) -> 20 | F4928: Panader | G4928: (Se panader) Marcher fièrement en se pavanant et en prenant des airs importants. | H4928: =MATCH(F4928,Liste!A:A,0) -> 3141 | I4928: =LEN(F4928) -> 7 | J4928: =SEARCH(" (",F4928) -> #VALUE! | K4928: Panader | L4928: (Se panader) Marcher fièrement en se pavanant et en prenant des airs importants. | M4928: =LEFT(F4928,J4928-1) -> #VALUE! | N4928: =RIGHT(F4928,I4928-J4928)&" "&G4928 -> #VALUE!
A4929: Paraphernal (Biens paraphernaux) : Biens propres d'une femme mariée qui restaient sous sa gestion personnelle (droit ancien). | B4929: =LEN(A4929) -> 125 | C4929: =SEARCH(":",A4929) -> 34 | D4929: =LEFT(A4929,C4929-2) -> Paraphernal (Biens paraphernaux) | E4929: =LEN(D4929) -> 32 | F4929: Paraphernal | G4929: (Biens paraphernaux) Biens propres d'une femme mariée qui restaient sous sa gestion personnelle (droit ancien). | H4929: =MATCH(F4929,Liste!A:A,0) -> 2264 | I4929: =LEN(F4929) -> 11 | J4929: =SEARCH(" (",F4929) -> #VALUE! | K4929: Paraphernal | L4929: (Biens paraphernaux) Biens propres d'une femme mariée qui restaient sous sa gestion personnelle (droit ancien). | M4929: =LEFT(F4929,J4929-1) -> #VALUE! | N4929: =RIGHT(F4929,I4929-J4929)&" "&G4929 -> #VALUE!
A4930: Partibus (In partibus) : Évêque titulaire d'un diocèse antique disparu situé en terre infidèle (expression signifiant "sans pouvoir réel"). | B4930: =LEN(A4930) -> 139 | C4930: =SEARCH(":",A4930) -> 24 | D4930: =LEFT(A4930,C4930-2) -> Partibus (In partibus) | E4930: =LEN(D4930) -> 22 | F4930: Partibus | G4930: (In partibus) Évêque titulaire d'un diocèse antique disparu situé en terre infidèle (expression signifiant "sans pouvoir réel"). | H4930: =MATCH(F4930,Liste!A:A,0) -> 2596 | I4930: =LEN(F4930) -> 8 | J4930: =SEARCH(" (",F4930) -> #VALUE! | K4930: Partibus | L4930: (In partibus) Évêque titulaire d'un diocèse antique disparu situé en terre infidèle (expression signifiant "sans pouvoir réel"). | M4930: =LEFT(F4930,J4930-1) -> #VALUE! | N4930: =RIGHT(F4930,I4930-J4930)&" "&G4930 -> #VALUE!
A4931: Pec (Hareng pec) : Hareng fraîchement pêché, salé en caque sur le bateau même. | B4931: =LEN(A4931) -> 78 | C4931: =SEARCH(":",A4931) -> 18 | D4931: =LEFT(A4931,C4931-2) -> Pec (Hareng pec) | E4931: =LEN(D4931) -> 16 | F4931: Pec | G4931: (Hareng pec) Hareng fraîchement pêché, salé en caque sur le bateau même. | H4931: =MATCH(F4931,Liste!A:A,0) -> 4827 | I4931: =LEN(F4931) -> 3 | J4931: =SEARCH(" (",F4931) -> #VALUE! | K4931: Pec | L4931: (Hareng pec) Hareng fraîchement pêché, salé en caque sur le bateau même. | M4931: =LEFT(F4931,J4931-1) -> #VALUE! | N4931: =RIGHT(F4931,I4931-J4931)&" "&G4931 -> #VALUE!
A4932: Pédauque (Reine Pédauque) : Reine mythologique représentée avec un pied d'oie sur les portails des cathédrales. | B4932: =LEN(A4932) -> 111 | C4932: =SEARCH(":",A4932) -> 27 | D4932: =LEFT(A4932,C4932-2) -> Pédauque (Reine Pédauque) | E4932: =LEN(D4932) -> 25 | F4932: Pédauque | G4932: (Reine Pédauque) Reine mythologique représentée avec un pied d'oie sur les portails des cathédrales. | H4932: =MATCH(F4932,Liste!A:A,0) -> 1347 | I4932: =LEN(F4932) -> 8 | J4932: =SEARCH(" (",F4932) -> #VALUE! | K4932: Pédauque | L4932: (Reine Pédauque) Reine mythologique représentée avec un pied d'oie sur les portails des cathédrales. | M4932: =LEFT(F4932,J4932-1) -> #VALUE! | N4932: =RIGHT(F4932,I4932-J4932)&" "&G4932 -> #VALUE!
A4933: Pelard (Bois pelard) : Tronc d'arbre abattu auquel on a retiré l'écorce pour en extraire le tanin. | B4933: =LEN(A4933) -> 98 | C4933: =SEARCH(":",A4933) -> 22 | D4933: =LEFT(A4933,C4933-2) -> Pelard (Bois pelard) | E4933: =LEN(D4933) -> 20 | F4933: Pelard | G4933: (Bois pelard) Tronc d'arbre abattu auquel on a retiré l'écorce pour en extraire le tanin. | H4933: =MATCH(F4933,Liste!A:A,0) -> 50 | I4933: =LEN(F4933) -> 6 | J4933: =SEARCH(" (",F4933) -> #VALUE! | K4933: Pelard | L4933: (Bois pelard) Tronc d'arbre abattu auquel on a retiré l'écorce pour en extraire le tanin. | M4933: =LEFT(F4933,J4933-1) -> #VALUE! | N4933: =RIGHT(F4933,I4933-J4933)&" "&G4933 -> #VALUE!
A4934: Péneau (Faire péneau) : Mettre les voiles d'un navire en ralingue pour arrêter sa course (marine ancienne). | B4934: =LEN(A4934) -> 107 | C4934: =SEARCH(":",A4934) -> 23 | D4934: =LEFT(A4934,C4934-2) -> Péneau (Faire péneau) | E4934: =LEN(D4934) -> 21 | F4934: Péneau | G4934: (Faire péneau) Mettre les voiles d'un navire en ralingue pour arrêter sa course (marine ancienne). | H4934: =MATCH(F4934,Liste!A:A,0) -> 895 | I4934: =LEN(F4934) -> 6 | J4934: =SEARCH(" (",F4934) -> #VALUE! | K4934: Péneau | L4934: (Faire péneau) Mettre les voiles d'un navire en ralingue pour arrêter sa course (marine ancienne). | M4934: =LEFT(F4934,J4934-1) -> #VALUE! | N4934: =RIGHT(F4934,I4934-J4934)&" "&G4934 -> #VALUE!
A4935: Perreyé (Mur perreyé) : Mur de fortification ou digue renforcé par un revêtement de grosses pierres de taille. | B4935: =LEN(A4935) -> 110 | C4935: =SEARCH(":",A4935) -> 23 | D4935: =LEFT(A4935,C4935-2) -> Perreyé (Mur perreyé) | E4935: =LEN(D4935) -> 21 | F4935: Perreyé | G4935: (Mur perreyé) Mur de fortification ou digue renforcé par un revêtement de grosses pierres de taille. | H4935: =MATCH(F4935,Liste!A:A,0) -> 4943 | I4935: =LEN(F4935) -> 7 | J4935: =SEARCH(" (",F4935) -> #VALUE! | K4935: Perreyé | L4935: (Mur perreyé) Mur de fortification ou digue renforcé par un revêtement de grosses pierres de taille. | M4935: =LEFT(F4935,J4935-1) -> #VALUE! | N4935: =RIGHT(F4935,I4935-J4935)&" "&G4935 -> #VALUE!
A4936: Piaculaire (Sacrifice piaculaire) : Sacrifice religieux expiatoire destiné à apaiser la colère des dieux et laver une souillure. | B4936: =LEN(A4936) -> 128 | C4936: =SEARCH(":",A4936) -> 35 | D4936: =LEFT(A4936,C4936-2) -> Piaculaire (Sacrifice piaculaire) | E4936: =LEN(D4936) -> 33 | F4936: Piaculaire | G4936: (Sacrifice piaculaire) Sacrifice religieux expiatoire destiné à apaiser la colère des dieux et laver une souillure. | H4936: =MATCH(F4936,Liste!A:A,0) -> 498 | I4936: =LEN(F4936) -> 10 | J4936: =SEARCH(" (",F4936) -> #VALUE! | K4936: Piaculaire | L4936: (Sacrifice piaculaire) Sacrifice religieux expiatoire destiné à apaiser la colère des dieux et laver une souillure. | M4936: =LEFT(F4936,J4936-1) -> #VALUE! | N4936: =RIGHT(F4936,I4936-J4936)&" "&G4936 -> #VALUE!
A4937: Picaresque (Roman picaresque) : Genre littéraire espagnol mettant en scène les aventures de héros marginaux, rusés et vagabonds (les picaros). | B4937: =LEN(A4937) -> 142 | C4937: =SEARCH(":",A4937) -> 31 | D4937: =LEFT(A4937,C4937-2) -> Picaresque (Roman picaresque) | E4937: =LEN(D4937) -> 29 | F4937: Picaresque | G4937: (Roman picaresque) Genre littéraire espagnol mettant en scène les aventures de héros marginaux, rusés et vagabonds (les picaros). | H4937: =MATCH(F4937,Liste!A:A,0) -> 1070 | I4937: =LEN(F4937) -> 10 | J4937: =SEARCH(" (",F4937) -> #VALUE! | K4937: Picaresque | L4937: (Roman picaresque) Genre littéraire espagnol mettant en scène les aventures de héros marginaux, rusés et vagabonds (les picaros). | M4937: =LEFT(F4937,J4937-1) -> #VALUE! | N4937: =RIGHT(F4937,I4937-J4937)&" "&G4937 -> #VALUE!
A4938: Prétantaine (Courir la prétantaine) : Courir les rues, courir d'un lieu à un autre à la recherche d'aventures frivoles. | B4938: =LEN(A4938) -> 123 | C4938: =SEARCH(":",A4938) -> 41 | D4938: =LEFT(A4938,C4938-2) -> Prétantaine (Courir la prétantaine) | E4938: =LEN(D4938) -> 39 | F4938: Prétantaine | G4938: (Courir la prétantaine) Courir les rues, courir d'un lieu à un autre à la recherche d'aventures frivoles. | H4938: =MATCH(F4938,Liste!A:A,0) -> 3903 | I4938: =LEN(F4938) -> 11 | J4938: =SEARCH(" (",F4938) -> #VALUE! | K4938: Prétantaine | L4938: (Courir la prétantaine) Courir les rues, courir d'un lieu à un autre à la recherche d'aventures frivoles. | M4938: =LEFT(F4938,J4938-1) -> #VALUE! | N4938: =RIGHT(F4938,I4938-J4938)&" "&G4938 -> #VALUE!
... A4978: Zymotique (Maladie zymotique) : Maladie infectieuse que l'on croyait jadis causée par un processus de fermentation interne dans le sang. | B4978: =LEN(A4978) -> 140 | C4978: =SEARCH(":",A4978) -> 35 | D4978: =LEFT(A4978,C4978-2) -> Zymotique (Maladie zymotique) | E4978: =LEN(D4978) -> 33 | F4978: Zymotique | G4978: (Maladie zymotique) Maladie infectieuse que l'on croyait jadis causée par un processus de fermentation interne dans le sang. | H4978: =MATCH(F4978,Liste!A:A,0) -> 4429 | I4978: =LEN(F4978) -> 9 | J4978: =SEARCH(" (",F4978) -> #VALUE! | K4978: Zymotique | L4978: (Maladie zymotique) Maladie infectieuse que l'on croyait jadis causée par un processus de fermentation interne dans le sang. | M4978: =LEFT(F4978,J4978-1) -> #VALUE! | N4978: =RIGHT(F4978,I4978-J4978)&" "&G4978 -> #VALUE!
A4979: Sans-culottides : Les cinq ou sept jours complémentaires ajoutés à la fin de l'année dans le calendrier républicain. | B4979: =LEN(A4979) -> 120 | C4979: =SEARCH(":",A4979) -> 21 | D4979: =LEFT(A4979,C4979-2) -> Sans-culottides | E4979: =LEN(D4979) -> 19 | F4979: Sans-culottides | G4979: Les cinq ou sept jours complémentaires ajoutés à la fin de l'année dans le calendrier républicain. | H4979: =MATCH(F4979,Liste!A:A,0) -> #N/A | I4979: =LEN(F4979) -> 15 | J4979: =SEARCH(" (",F4979) -> #VALUE! | K4979: #VALUE! | L4979: #VALUE! | M4979: =LEFT(F4979,J4979-1) -> #VALUE! | N4979: =RIGHT(F4979,I4979-J4979)&" "&G4979 -> #VALUE!
A4980: Apophthegme : Parole mémorable, sentence courte et percutante d'un personnage célèbre. | B4980: =LEN(A4980) -> 86 | C4980: =SEARCH(":",A4980) -> 13 | D4980: =LEFT(A4980,C4980-2) -> Apophthegme | E4980: =LEN(D4980) -> 11 | F4980: Apophthegme | G4980: Parole mémorable, sentence courte et percutante d'un personnage célèbre. | H4980: =MATCH(F4980,Liste!A:A,0) -> 2637 | I4980: =LEN(F4980) -> 11 | J4980: =SEARCH(" (",F4980) -> #VALUE! | K4980: #VALUE! | L4980: #VALUE! | M4980: =LEFT(F4980,J4980-1) -> #VALUE! | N4980: =RIGHT(F4980,I4980-J4980)&" "&G4980 -> #VALUE!
A4981: Bachelette : Jeune fille ou jeune femme en vieux français. | B4981: =LEN(A4981) -> 58 | C4981: =SEARCH(":",A4981) -> 12 | D4981: =LEFT(A4981,C4981-2) -> Bachelette | E4981: =LEN(D4981) -> 10 | F4981: Bachelette | G4981: Jeune fille ou jeune femme en vieux français. | H4981: =MATCH(F4981,Liste!A:A,0) -> 1892 | I4981: =LEN(F4981) -> 10 | J4981: =SEARCH(" (",F4981) -> #VALUE! | K4981: #VALUE! | L4981: #VALUE! | M4981: =LEFT(F4981,J4981-1) -> #VALUE! | N4981: =RIGHT(F4981,I4981-J4981)&" "&G4981 -> #VALUE!
A4982: Baratre (ou Barathre) : Gouffre profond à Athènes où l'on jetait les condamnés à mort ; les enfers. | B4982: =LEN(A4982) -> 99 | C4982: =SEARCH(":",A4982) -> 23 | D4982: =LEFT(A4982,C4982-2) -> Baratre (ou Barathre) | E4982: =LEN(D4982) -> 21 | F4982: =K4982 -> Baratre | G4982: =L4982 -> (ou Barathre) Gouffre profond à Athènes où l'on jetait les condamnés à mort ; les enfers. | H4982: =MATCH(F4982,Liste!A:A,0) -> 3746 | I4982: =LEN(F4982) -> 7 | J4982: =SEARCH(" (",F4982) -> #VALUE! | K4982: Baratre | L4982: (ou Barathre) Gouffre profond à Athènes où l'on jetait les condamnés à mort ; les enfers. | M4982: =LEFT(F4982,J4982-1) -> #VALUE! | N4982: =RIGHT(F4982,I4982-J4982)&" "&G4982 -> #VALUE!
A4983: Bélandre : Petit navire de transport à fond plat utilisé sur les canaux et rivières. | B4983: =LEN(A4983) -> 84 | C4983: =SEARCH(":",A4983) -> 10 | D4983: =LEFT(A4983,C4983-2) -> Bélandre | E4983: =LEN(D4983) -> 8 | F4983: Bélandre | G4983: Petit navire de transport à fond plat utilisé sur les canaux et rivières. | H4983: =MATCH(F4983,Liste!A:A,0) -> 3297 | I4983: =LEN(F4983) -> 8 | J4983: =SEARCH(" (",F4983) -> #VALUE! | K4983: #VALUE! | L4983: #VALUE! | M4983: =LEFT(F4983,J4983-1) -> #VALUE! | N4983: =RIGHT(F4983,I4983-J4983)&" "&G4983 -> #VALUE!
A4984: Chryséléphantine : Statue antique faite d'or (pour les vêtements) et d'ivoire (pour la chair). | B4984: =LEN(A4984) -> 94 | C4984: =SEARCH(":",A4984) -> 18 | D4984: =LEFT(A4984,C4984-2) -> Chryséléphantine | E4984: =LEN(D4984) -> 16 | F4984: Chryséléphantine | G4984: Statue antique faite d'or (pour les vêtements) et d'ivoire (pour la chair). | H4984: =MATCH(F4984,Liste!A:A,0) -> 2722 | I4984: =LEN(F4984) -> 16 | J4984: =SEARCH(" (",F4984) -> #VALUE! | K4984: #VALUE! | L4984: #VALUE! | M4984: =LEFT(F4984,J4984-1) -> #VALUE! | N4984: =RIGHT(F4984,I4984-J4984)&" "&G4984 -> #VALUE!
A4985: Chtonien (ou Chthonien) : Relatif aux divinités souterraines et infernales de la Terre. | B4985: =LEN(A4985) -> 87 | C4985: =SEARCH(":",A4985) -> 25 | D4985: =LEFT(A4985,C4985-2) -> Chtonien (ou Chthonien) | E4985: =LEN(D4985) -> 23 | F4985: =K4985 -> Chtonien | G4985: =L4985 -> (ou Chthonien) Relatif aux divinités souterraines et infernales de la Terre. | H4985: =MATCH(F4985,Liste!A:A,0) -> 3744 | I4985: =LEN(F4985) -> 8 | J4985: =SEARCH(" (",F4985) -> #VALUE! | K4985: Chtonien | L4985: (ou Chthonien) Relatif aux divinités souterraines et infernales de la Terre. | M4985: =LEFT(F4985,J4985-1) -> #VALUE! | N4985: =RIGHT(F4985,I4985-J4985)&" "&G4985 -> #VALUE!
A4986: Éleuthénie : Fête ou célébration de la liberté dans la Grèce antique. | B4986: =LEN(A4986) -> 69 | C4986: =SEARCH(":",A4986) -> 12 | D4986: =LEFT(A4986,C4986-2) -> Éleuthénie | E4986: =LEN(D4986) -> 10 | F4986: Éleuthénie | G4986: Fête ou célébration de la liberté dans la Grèce antique. | H4986: =MATCH(F4986,Liste!A:A,0) -> 627 | I4986: =LEN(F4986) -> 10 | J4986: =SEARCH(" (",F4986) -> #VALUE! | K4986: #VALUE! | L4986: #VALUE! | M4986: =LEFT(F4986,J4986-1) -> #VALUE! | N4986: =RIGHT(F4986,I4986-J4986)&" "&G4986 -> #VALUE!
A4987: Éphélides : Nom scientifique et médical donné aux taches de rousseur. | B4987: =LEN(A4987) -> 69 | C4987: =SEARCH(":",A4987) -> 11 | D4987: =LEFT(A4987,C4987-2) -> Éphélides | E4987: =LEN(D4987) -> 9 | F4987: Éphélides | G4987: Nom scientifique et médical donné aux taches de rousseur. | H4987: =MATCH(F4987,Liste!A:A,0) -> 2027 | I4987: =LEN(F4987) -> 9 | J4987: =SEARCH(" (",F4987) -> #VALUE! | K4987: #VALUE! | L4987: #VALUE! | M4987: =LEFT(F4987,J4987-1) -> #VALUE! | N4987: =RIGHT(F4987,I4987-J4987)&" "&G4987 -> #VALUE!
A4988: Epique : Qui raconte des exploits héroïques et grandioses. | B4988: =LEN(A4988) -> 58 | C4988: =SEARCH(":",A4988) -> 8 | D4988: =LEFT(A4988,C4988-2) -> Epique | E4988: =LEN(D4988) -> 6 | F4988: Epique | G4988: Qui raconte des exploits héroïques et grandioses. | H4988: =MATCH(F4988,Liste!A:A,0) -> 355 | I4988: =LEN(F4988) -> 6 | J4988: =SEARCH(" (",F4988) -> #VALUE! | K4988: #VALUE! | L4988: #VALUE! | M4988: =LEFT(F4988,J4988-1) -> #VALUE! | N4988: =RIGHT(F4988,I4988-J4988)&" "&G4988 -> #VALUE!
A4989: Épulons : Prêtres romains chargés de l'organisation des festins sacrés lors des grands jeux. | B4989: =LEN(A4989) -> 92 | C4989: =SEARCH(":",A4989) -> 9 | D4989: =LEFT(A4989,C4989-2) -> Épulons | E4989: =LEN(D4989) -> 7 | F4989: Épulons | G4989: Prêtres romains chargés de l'organisation des festins sacrés lors des grands jeux. | H4989: =MATCH(F4989,Liste!A:A,0) -> 1321 | I4989: =LEN(F4989) -> 7 | J4989: =SEARCH(" (",F4989) -> #VALUE! | K4989: #VALUE! | L4989: #VALUE! | M4989: =LEFT(F4989,J4989-1) -> #VALUE! | N4989: =RIGHT(F4989,I4989-J4989)&" "&G4989 -> #VALUE!
A4990: Exégète : Spécialiste de l'interprétation critique et de l'explication des textes sacrés ou anciens. | B4990: =LEN(A4990) -> 100 | C4990: =SEARCH(":",A4990) -> 9 | D4990: =LEFT(A4990,C4990-2) -> Exégète | E4990: =LEN(D4990) -> 7 | F4990: Exégète | G4990: Spécialiste de l'interprétation critique et de l'explication des textes sacrés ou anciens. | H4990: =MATCH(F4990,Liste!A:A,0) -> #N/A | I4990: =LEN(F4990) -> 7 | J4990: =SEARCH(" (",F4990) -> #VALUE! | K4990: #VALUE! | L4990: #VALUE! | M4990: =LEFT(F4990,J4990-1) -> #VALUE! | N4990: =RIGHT(F4990,I4990-J4990)&" "&G4990 -> #VALUE!
A4991: Glaie : Plante aquatique des marais ressemblant à l'iris (le glaïeul sauvage). | B4991: =LEN(A4991) -> 78 | C4991: =SEARCH(":",A4991) -> 7 | D4991: =LEFT(A4991,C4991-2) -> Glaie | E4991: =LEN(D4991) -> 5 | F4991: Glaie | G4991: Plante aquatique des marais ressemblant à l'iris (le glaïeul sauvage). | H4991: =MATCH(F4991,Liste!A:A,0) -> 3463 | I4991: =LEN(F4991) -> 5 | J4991: =SEARCH(" (",F4991) -> #VALUE! | K4991: #VALUE! | L4991: #VALUE! | M4991: =LEFT(F4991,J4991-1) -> #VALUE! | N4991: =RIGHT(F4991,I4991-J4991)&" "&G4991 -> #VALUE!
A4992: Gone, gonne : Tunique longue portée au Moyen Âge ; ou enfant dans le parler lyonnais. | B4992: =LEN(A4992) -> 85 | C4992: =SEARCH(":",A4992) -> 13 | D4992: =LEFT(A4992,C4992-2) -> Gone, gonne | E4992: =LEN(D4992) -> 11 | F4992: Gone, gonne | G4992: Tunique longue portée au Moyen Âge ; ou enfant dans le parler lyonnais. | H4992: =MATCH(F4992,Liste!A:A,0) -> 299 | I4992: =LEN(F4992) -> 11 | J4992: =SEARCH(" (",F4992) -> #VALUE! | K4992: #VALUE! | L4992: #VALUE! | M4992: =LEFT(F4992,J4992-1) -> #VALUE! | N4992: =RIGHT(F4992,I4992-J4992)&" "&G4992 -> #VALUE!
A4993: Gueuser : Mener une vie de mendiant, quémander sa nourriture ou vivre misérablement. | B4993: =LEN(A4993) -> 84 | C4993: =SEARCH(":",A4993) -> 9 | D4993: =LEFT(A4993,C4993-2) -> Gueuser | E4993: =LEN(D4993) -> 7 | F4993: Gueuser | G4993: Mener une vie de mendiant, quémander sa nourriture ou vivre misérablement. | H4993: =MATCH(F4993,Liste!A:A,0) -> 79 | I4993: =LEN(F4993) -> 7 | J4993: =SEARCH(" (",F4993) -> #VALUE! | K4993: #VALUE! | L4993: #VALUE! | M4993: =LEFT(F4993,J4993-1) -> #VALUE! | N4993: =RIGHT(F4993,I4993-J4993)&" "&G4993 -> #VALUE!
A4994: Higoumène : Supérieur ou abbé d'un monastère dans l'Église chrétienne d'Orient (orthodoxe). | B4994: =LEN(A4994) -> 91 | C4994: =SEARCH(":",A4994) -> 11 | D4994: =LEFT(A4994,C4994-2) -> Higoumène | E4994: =LEN(D4994) -> 9 | F4994: Higoumène | G4994: Supérieur ou abbé d'un monastère dans l'Église chrétienne d'Orient (orthodoxe). | H4994: =MATCH(F4994,Liste!A:A,0) -> 130 | I4994: =LEN(F4994) -> 9 | J4994: =SEARCH(" (",F4994) -> #VALUE! | K4994: #VALUE! | L4994: #VALUE! | M4994: =LEFT(F4994,J4994-1) -> #VALUE! | N4994: =RIGHT(F4994,I4994-J4994)&" "&G4994 -> #VALUE!
A4995: Jaquemart : Automate de fer ou de bronze qui frappe les heures avec un marteau sur une cloche. | B4995: =LEN(A4995) -> 94 | C4995: =SEARCH(":",A4995) -> 11 | D4995: =LEFT(A4995,C4995-2) -> Jaquemart | E4995: =LEN(D4995) -> 9 | F4995: Jaquemart | G4995: Automate de fer ou de bronze qui frappe les heures avec un marteau sur une cloche. | H4995: =MATCH(F4995,Liste!A:A,0) -> 2769 | I4995: =LEN(F4995) -> 9 | J4995: =SEARCH(" (",F4995) -> #VALUE! | K4995: #VALUE! | L4995: #VALUE! | M4995: =LEFT(F4995,J4995-1) -> #VALUE! | N4995: =RIGHT(F4995,I4995-J4995)&" "&G4995 -> #VALUE!
A4996: Jaquet : Ancien nom populaire donné au jeu de trictrac ou de backgammon ; ou le lièvre. | B4996: =LEN(A4996) -> 87 | C4996: =SEARCH(":",A4996) -> 8 | D4996: =LEFT(A4996,C4996-2) -> Jaquet | E4996: =LEN(D4996) -> 6 | F4996: Jaquet | G4996: Ancien nom populaire donné au jeu de trictrac ou de backgammon ; ou le lièvre. | H4996: =MATCH(F4996,Liste!A:A,0) -> 819 | I4996: =LEN(F4996) -> 6 | J4996: =SEARCH(" (",F4996) -> #VALUE! | K4996: #VALUE! | L4996: #VALUE! | M4996: =LEFT(F4996,J4996-1) -> #VALUE! | N4996: =RIGHT(F4996,I4996-J4996)&" "&G4996 -> #VALUE!
A4997: Jaquette : Vêtement masculin de cérémonie à longues basques ; ou jaque courte au Moyen Âge. | B4997: =LEN(A4997) -> 91 | C4997: =SEARCH(":",A4997) -> 10 | D4997: =LEFT(A4997,C4997-2) -> Jaquette | E4997: =LEN(D4997) -> 8 | F4997: Jaquette | G4997: Vêtement masculin de cérémonie à longues basques ; ou jaque courte au Moyen Âge. | H4997: =MATCH(F4997,Liste!A:A,0) -> 2484 | I4997: =LEN(F4997) -> 8 | J4997: =SEARCH(" (",F4997) -> #VALUE! | K4997: #VALUE! | L4997: #VALUE! | M4997: =LEFT(F4997,J4997-1) -> #VALUE! | N4997: =RIGHT(F4997,I4997-J4997)&" "&G4997 -> #VALUE!
... A5051: Surérogation : Action méritoire qui va au-delà de ce qui est strictement exigé par le devoir ou la loi. | B5051: =LEN(A5051) -> 103 | C5051: =SEARCH(":",A5051) -> 14 | D5051: =LEFT(A5051,C5051-2) -> Surérogation | E5051: =LEN(D5051) -> 12 | F5051: Surérogation | G5051: Action méritoire qui va au-delà de ce qui est strictement exigé par le devoir ou la loi. | H5051: =MATCH(F5051,Liste!A:A,0) -> 36 | I5051: =LEN(F5051) -> 12 | J5051: =SEARCH(" (",F5051) -> #VALUE! | K5051: #VALUE! | L5051: #VALUE! | M5051: =LEFT(F5051,J5051-1) -> #VALUE! | N5051: =RIGHT(F5051,I5051-J5051)&" "&G5051 -> #VALUE!
A5052: Surge (Laine surge) : Laine brute qui n'a pas été lavée ni dégraissée après la tonte du mouton. | B5052: =LEN(A5052) -> 95 | C5052: =SEARCH(":",A5052) -> 21 | D5052: =LEFT(A5052,C5052-2) -> Surge (Laine surge) | E5052: =LEN(D5052) -> 19 | F5052: =K5052 -> Surge | G5052: =L5052 -> (Laine surge) Laine brute qui n'a pas été lavée ni dégraissée après la tonte du mouton. | H5052: =MATCH(F5052,Liste!A:A,0) -> 380 | I5052: =LEN(F5052) -> 5 | J5052: =SEARCH(" (",F5052) -> #VALUE! | K5052: Surge | L5052: (Laine surge) Laine brute qui n'a pas été lavée ni dégraissée après la tonte du mouton. | M5052: =LEFT(F5052,J5052-1) -> #VALUE! | N5052: =RIGHT(F5052,I5052-J5052)&" "&G5052 -> #VALUE!
A5053: Surlé : Qui a commencé à s'aigrir, en parlant du lait ou d'un fluide. | B5053: =LEN(A5053) -> 69 | C5053: =SEARCH(":",A5053) -> 7 | D5053: =LEFT(A5053,C5053-2) -> Surlé | E5053: =LEN(D5053) -> 5 | F5053: Surlé | G5053: Qui a commencé à s'aigrir, en parlant du lait ou d'un fluide. | H5053: =MATCH(F5053,Liste!A:A,0) -> 3112 | I5053: =LEN(F5053) -> 5 | J5053: =SEARCH(" (",F5053) -> #VALUE! | K5053: #VALUE! | L5053: #VALUE! | M5053: =LEFT(F5053,J5053-1) -> #VALUE! | N5053: =RIGHT(F5053,I5053-J5053)&" "&G5053 -> #VALUE!
A5054: Surranation : État d'un acte officiel qui a perdu sa validité légale pour avoir dépassé sa date limite (péremption). | B5054: =LEN(A5054) -> 116 | C5054: =SEARCH(":",A5054) -> 13 | D5054: =LEFT(A5054,C5054-2) -> Surranation | E5054: =LEN(D5054) -> 11 | F5054: Surranation | G5054: État d'un acte officiel qui a perdu sa validité légale pour avoir dépassé sa date limite (péremption). | H5054: =MATCH(F5054,Liste!A:A,0) -> 4080 | I5054: =LEN(F5054) -> 11 | J5054: =SEARCH(" (",F5054) -> #VALUE! | K5054: #VALUE! | L5054: #VALUE! | M5054: =LEFT(F5054,J5054-1) -> #VALUE! | N5054: =RIGHT(F5054,I5054-J5054)&" "&G5054 -> #VALUE!
A5055: Sybarite : Personne qui recherche les plaisirs de la vie, le luxe et le confort d'une manière raffinée et efféminée. | B5055: =LEN(A5055) -> 116 | C5055: =SEARCH(":",A5055) -> 10 | D5055: =LEFT(A5055,C5055-2) -> Sybarite | E5055: =LEN(D5055) -> 8 | F5055: Sybarite | G5055: Personne qui recherche les plaisirs de la vie, le luxe et le confort d'une manière raffinée et efféminée. | H5055: =MATCH(F5055,Liste!A:A,0) -> 2017 | I5055: =LEN(F5055) -> 8 | J5055: =SEARCH(" (",F5055) -> #VALUE! | K5055: #VALUE! | L5055: #VALUE! | M5055: =LEFT(F5055,J5055-1) -> #VALUE! | N5055: =RIGHT(F5055,I5055-J5055)&" "&G5055 -> #VALUE!
A5056: Sycamor : Variété de figuier d'Égypte antique ; ou grand arbre de la famille des érables. | B5056: =LEN(A5056) -> 89 | C5056: =SEARCH(":",A5056) -> 9 | D5056: =LEFT(A5056,C5056-2) -> Sycamor | E5056: =LEN(D5056) -> 7 | F5056: Sycamor | G5056: Variété de figuier d'Égypte antique ; ou grand arbre de la famille des érables. | H5056: =MATCH(F5056,Liste!A:A,0) -> 2611 | I5056: =LEN(F5056) -> 7 | J5056: =SEARCH(" (",F5056) -> #VALUE! | K5056: #VALUE! | L5056: #VALUE! | M5056: =LEFT(F5056,J5056-1) -> #VALUE! | N5056: =RIGHT(F5056,I5056-J5056)&" "&G5056 -> #VALUE!
A5057: Sylphe : Génie invisible, gracieux et aérien dans les légendes mythologiques nordiques. | B5057: =LEN(A5057) -> 87 | C5057: =SEARCH(":",A5057) -> 8 | D5057: =LEFT(A5057,C5057-2) -> Sylphe | E5057: =LEN(D5057) -> 6 | F5057: Sylphe | G5057: Génie invisible, gracieux et aérien dans les légendes mythologiques nordiques. | H5057: =MATCH(F5057,Liste!A:A,0) -> 927 | I5057: =LEN(F5057) -> 6 | J5057: =SEARCH(" (",F5057) -> #VALUE! | K5057: #VALUE! | L5057: #VALUE! | M5057: =LEFT(F5057,J5057-1) -> #VALUE! | N5057: =RIGHT(F5057,I5057-J5057)&" "&G5057 -> #VALUE!
A5058: Sylvain : Divinité protectrice des forêts et des bois dans la mythologie romaine. | B5058: =LEN(A5058) -> 81 | C5058: =SEARCH(":",A5058) -> 9 | D5058: =LEFT(A5058,C5058-2) -> Sylvain | E5058: =LEN(D5058) -> 7 | F5058: Sylvain | G5058: Divinité protectrice des forêts et des bois dans la mythologie romaine. | H5058: =MATCH(F5058,Liste!A:A,0) -> 2452 | I5058: =LEN(F5058) -> 7 | J5058: =SEARCH(" (",F5058) -> #VALUE! | K5058: #VALUE! | L5058: #VALUE! | M5058: =LEFT(F5058,J5058-1) -> #VALUE! | N5058: =RIGHT(F5058,I5058-J5058)&" "&G5058 -> #VALUE!
A5059: Symblépharon : Adhérence cicatricielle anormale de la paupière au globe oculaire (terme médical). | B5059: =LEN(A5059) -> 97 | C5059: =SEARCH(":",A5059) -> 14 | D5059: =LEFT(A5059,C5059-2) -> Symblépharon | E5059: =LEN(D5059) -> 12 | F5059: Symblépharon | G5059: Adhérence cicatricielle anormale de la paupière au globe oculaire (terme médical). | H5059: =MATCH(F5059,Liste!A:A,0) -> 3745 | I5059: =LEN(F5059) -> 12 | J5059: =SEARCH(" (",F5059) -> #VALUE! | K5059: #VALUE! | L5059: #VALUE! | M5059: =LEFT(F5059,J5059-1) -> #VALUE! | N5059: =RIGHT(F5059,I5059-J5059)&" "&G5059 -> #VALUE!
A5060: Symploque : Figure consistant à répéter un mot en début de phrase et un autre mot en fin de phrase. | B5060: =LEN(A5060) -> 99 | C5060: =SEARCH(":",A5060) -> 11 | D5060: =LEFT(A5060,C5060-2) -> Symploque | E5060: =LEN(D5060) -> 9 | F5060: Symploque | G5060: Figure consistant à répéter un mot en début de phrase et un autre mot en fin de phrase. | H5060: =MATCH(F5060,Liste!A:A,0) -> 3668 | I5060: =LEN(F5060) -> 9 | J5060: =SEARCH(" (",F5060) -> #VALUE! | K5060: #VALUE! | L5060: #VALUE! | M5060: =LEFT(F5060,J5060-1) -> #VALUE! | N5060: =RIGHT(F5060,I5060-J5060)&" "&G5060 -> #VALUE!
A5061: Symposiaque : Relatif aux banquets, aux festins philosophiques et aux réunions de buveurs dans l'Antiquité. | B5061: =LEN(A5061) -> 107 | C5061: =SEARCH(":",A5061) -> 13 | D5061: =LEFT(A5061,C5061-2) -> Symposiaque | E5061: =LEN(D5061) -> 11 | F5061: Symposiaque | G5061: Relatif aux banquets, aux festins philosophiques et aux réunions de buveurs dans l'Antiquité. | H5061: =MATCH(F5061,Liste!A:A,0) -> 712 | I5061: =LEN(F5061) -> 11 | J5061: =SEARCH(" (",F5061) -> #VALUE! | K5061: #VALUE! | L5061: #VALUE! | M5061: =LEFT(F5061,J5061-1) -> #VALUE! | N5061: =RIGHT(F5061,I5061-J5061)&" "&G5061 -> #VALUE!
A5062: Synalèphe : Contraction ou fusion de deux voyelles successives en une seule syllabe en poésie. | B5062: =LEN(A5062) -> 94 | C5062: =SEARCH(":",A5062) -> 11 | D5062: =LEFT(A5062,C5062-2) -> Synalèphe | E5062: =LEN(D5062) -> 9 | F5062: Synalèphe | G5062: Contraction ou fusion de deux voyelles successives en une seule syllabe en poésie. | H5062: =MATCH(F5062,Liste!A:A,0) -> 2357 | I5062: =LEN(F5062) -> 9 | J5062: =SEARCH(" (",F5062) -> #VALUE! | K5062: #VALUE! | L5062: #VALUE! | M5062: =LEFT(F5062,J5062-1) -> #VALUE! | N5062: =RIGHT(F5062,I5062-J5062)&" "&G5062 -> #VALUE!
A5063: Synarchie : Système de gouvernement où le pouvoir est exercé simultanément par plusieurs autorités ou un groupe secret. | B5063: =LEN(A5063) -> 119 | C5063: =SEARCH(":",A5063) -> 11 | D5063: =LEFT(A5063,C5063-2) -> Synarchie | E5063: =LEN(D5063) -> 9 | F5063: Synarchie | G5063: Système de gouvernement où le pouvoir est exercé simultanément par plusieurs autorités ou un groupe secret. | H5063: =MATCH(F5063,Liste!A:A,0) -> 44 | I5063: =LEN(F5063) -> 9 | J5063: =SEARCH(" (",F5063) -> #VALUE! | K5063: #VALUE! | L5063: #VALUE! | M5063: =LEFT(F5063,J5063-1) -> #VALUE! | N5063: =RIGHT(F5063,I5063-J5063)&" "&G5063 -> #VALUE!
A5064: Synaxe : Assemblée religieuse chrétienne primitive réunie pour la prière et la liturgie. | B5064: =LEN(A5064) -> 88 | C5064: =SEARCH(":",A5064) -> 8 | D5064: =LEFT(A5064,C5064-2) -> Synaxe | E5064: =LEN(D5064) -> 6 | F5064: Synaxe | G5064: Assemblée religieuse chrétienne primitive réunie pour la prière et la liturgie. | H5064: =MATCH(F5064,Liste!A:A,0) -> 546 | I5064: =LEN(F5064) -> 6 | J5064: =SEARCH(" (",F5064) -> #VALUE! | K5064: #VALUE! | L5064: #VALUE! | M5064: =LEFT(F5064,J5064-1) -> #VALUE! | N5064: =RIGHT(F5064,I5064-J5064)&" "&G5064 -> #VALUE!
... A5069: Syringe : Flûte de Pan traditionnelle faite de roseaux assemblés ; ou conduit souterrain. | B5069: =LEN(A5069) -> 89 | C5069: =SEARCH(":",A5069) -> 9 | D5069: =LEFT(A5069,C5069-2) -> Syringe | E5069: =LEN(D5069) -> 7 | F5069: Syringe | G5069: Flûte de Pan traditionnelle faite de roseaux assemblés ; ou conduit souterrain. | H5069: =MATCH(F5069,Liste!A:A,0) -> 1451 | I5069: =LEN(F5069) -> 7 | J5069: =SEARCH(" (",F5069) -> #VALUE! | K5069: #VALUE! | L5069: #VALUE! | M5069: =LEFT(F5069,J5069-1) -> #VALUE! | N5069: =RIGHT(F5069,I5069-J5069)&" "&G5069 -> #VALUE!
A5070: Syrvante (ou Servante) : Sorte de court poème ou de pièce satirique médiévale en vieux français. | B5070: =LEN(A5070) -> 96 | C5070: =SEARCH(":",A5070) -> 24 | D5070: =LEFT(A5070,C5070-2) -> Syrvante (ou Servante) | E5070: =LEN(D5070) -> 22 | F5070: Syrvante | G5070: (ou Servante) Sorte de court poème ou de pièce satirique médiévale en vieux français. | H5070: =MATCH(F5070,Liste!A:A,0) -> 4606 | I5070: =LEN(F5070) -> 8 | J5070: =SEARCH(" (",F5070) -> #VALUE! | K5070: Syrvante | L5070: (ou Servante) Sorte de court poème ou de pièce satirique médiévale en vieux français. | M5070: =LEFT(F5070,J5070-1) -> #VALUE! | N5070: =RIGHT(F5070,I5070-J5070)&" "&G5070 -> #VALUE!
A5071: Taluter : Donner une inclinaison en pente oblique à un terrain ou à un fossé de route. | B5071: =LEN(A5071) -> 86 | C5071: =SEARCH(":",A5071) -> 9 | D5071: =LEFT(A5071,C5071-2) -> Taluter | E5071: =LEN(D5071) -> 7 | F5071: Taluter | G5071: Donner une inclinaison en pente oblique à un terrain ou à un fossé de route. | H5071: =MATCH(F5071,Liste!A:A,0) -> 137 | I5071: =LEN(F5071) -> 7 | J5071: =SEARCH(" (",F5071) -> #VALUE! | K5071: #VALUE! | L5071: #VALUE! | M5071: =LEFT(F5071,J5071-1) -> #VALUE! | N5071: =RIGHT(F5071,I5071-J5071)&" "&G5071 -> #VALUE!
A5072: Tarbouch : Bonnet de feutre rouge rigide, orné d'un gland noir, porté traditionnellement en Orient. | B5072: =LEN(A5072) -> 99 | C5072: =SEARCH(":",A5072) -> 10 | D5072: =LEFT(A5072,C5072-2) -> Tarbouch | E5072: =LEN(D5072) -> 8 | F5072: Tarbouch | G5072: Bonnet de feutre rouge rigide, orné d'un gland noir, porté traditionnellement en Orient. | H5072: =MATCH(F5072,Liste!A:A,0) -> 1152 | I5072: =LEN(F5072) -> 8 | J5072: =SEARCH(" (",F5072) -> #VALUE! | K5072: #VALUE! | L5072: #VALUE! | M5072: =LEFT(F5072,J5072-1) -> #VALUE! | N5072: =RIGHT(F5072,I5072-J5072)&" "&G5072 -> #VALUE!
A5073: Tarpéienne (Roche tarpéienne) : Crête rocheuse du Capitole à Rome d'où l'on jetait les traîtres dans l'Antiquité. | B5073: =LEN(A5073) -> 113 | C5073: =SEARCH(":",A5073) -> 31 | D5073: =LEFT(A5073,C5073-2) -> Tarpéienne (Roche tarpéienne) | E5073: =LEN(D5073) -> 29 | F5073: Tarpéienne | G5073: (Roche tarpéienne) Crête rocheuse du Capitole à Rome d'où l'on jetait les traîtres dans l'Antiquité. | H5073: =MATCH(F5073,Liste!A:A,0) -> 1318 | I5073: =LEN(F5073) -> 10 | J5073: =SEARCH(" (",F5073) -> #VALUE! | K5073: Tarpéienne | L5073: (Roche tarpéienne) Crête rocheuse du Capitole à Rome d'où l'on jetait les traîtres dans l'Antiquité. | M5073: =LEFT(F5073,J5073-1) -> #VALUE! | N5073: =RIGHT(F5073,I5073-J5073)&" "&G5073 -> #VALUE!
A5074: Taudis : Logement misérable, sale, exigu et mal entretenu. | B5074: =LEN(A5074) -> 58 | C5074: =SEARCH(":",A5074) -> 8 | D5074: =LEFT(A5074,C5074-2) -> Taudis | E5074: =LEN(D5074) -> 6 | F5074: Taudis | G5074: Logement misérable, sale, exigu et mal entretenu. | H5074: =MATCH(F5074,Liste!A:A,0) -> 2178 | I5074: =LEN(F5074) -> 6 | J5074: =SEARCH(" (",F5074) -> #VALUE! | K5074: #VALUE! | L5074: #VALUE! | M5074: =LEFT(F5074,J5074-1) -> #VALUE! | N5074: =RIGHT(F5074,I5074-J5074)&" "&G5074 -> #VALUE!
A5075: Thiephaigne ou Tiphaine : Ancien nom traditionnel donné à la fête de l'Épiphanie au Moyen Âge. | B5075: =LEN(A5075) -> 94 | C5075: =SEARCH(":",A5075) -> 25 | D5075: =LEFT(A5075,C5075-2) -> Thiephaigne ou Tiphaine | E5075: =LEN(D5075) -> 23 | F5075: Thiephaigne ou Tiphaine | G5075: Ancien nom traditionnel donné à la fête de l'Épiphanie au Moyen Âge. | H5075: =MATCH(F5075,Liste!A:A,0) -> 1874 | I5075: =LEN(F5075) -> 23 | J5075: =SEARCH(" (",F5075) -> #VALUE! | K5075: #VALUE! | L5075: #VALUE! | M5075: =LEFT(F5075,J5075-1) -> #VALUE! | N5075: =RIGHT(F5075,I5075-J5075)&" "&G5075 -> #VALUE!
A5076: Turcie : Levée de terre ou digue de maçonnerie construite le long de la Loire pour empêcher les crues. | B5076: =LEN(A5076) -> 102 | C5076: =SEARCH(":",A5076) -> 8 | D5076: =LEFT(A5076,C5076-2) -> Turcie | E5076: =LEN(D5076) -> 6 | F5076: Turcie | G5076: Levée de terre ou digue de maçonnerie construite le long de la Loire pour empêcher les crues. | H5076: =MATCH(F5076,Liste!A:A,0) -> 2193 | I5076: =LEN(F5076) -> 6 | J5076: =SEARCH(" (",F5076) -> #VALUE! | K5076: #VALUE! | L5076: #VALUE! | M5076: =LEFT(F5076,J5076-1) -> #VALUE! | N5076: =RIGHT(F5076,I5076-J5076)&" "&G5076 -> #VALUE!
A5077: Wteringue (ou Wateringue) : Réseau de canaux et d'écluses gérant le drainage et l'évacuation des eaux dans les polders. | B5077: =LEN(A5077) -> 119 | C5077: =SEARCH(":",A5077) -> 27 | D5077: =LEFT(A5077,C5077-2) -> Wteringue (ou Wateringue) | E5077: =LEN(D5077) -> 25 | F5077: Wteringue | G5077: (ou Wateringue) Réseau de canaux et d'écluses gérant le drainage et l'évacuation des eaux dans les polders. | H5077: =MATCH(F5077,Liste!A:A,0) -> 2725 | I5077: =LEN(F5077) -> 9 | J5077: =SEARCH(" (",F5077) -> #VALUE! | K5077: Wteringue | L5077: (ou Wateringue) Réseau de canaux et d'écluses gérant le drainage et l'évacuation des eaux dans les polders. | M5077: =LEFT(F5077,J5077-1) -> #VALUE! | N5077: =RIGHT(F5077,I5077-J5077)&" "&G5077 -> #VALUE!
